shiter/__init__.py
shiter/print.py
shiter-0.1.2.dist-info/LICENSE
shiter-0.1.2.dist-info/METADATA
shiter-0.1.2.dist-info/WHEEL
shiter-0.1.2.dist-info/top_level.txt
shiter-0.1.2.dist-info/RECORD
